iDEA/__init__.py
iDEA/interactions.py
iDEA/observables.py
iDEA/reverse_engineering.py
iDEA/state.py
iDEA/system.py
iDEA/utilities.py
iDEA/methods/__init__.py
iDEA/methods/hartree.py
iDEA/methods/hartree_fock.py
iDEA/methods/hybrid.py
iDEA/methods/interacting.py
iDEA/methods/kssce.py
iDEA/methods/lda.py
iDEA/methods/non_interacting.py
idea_latest-1.0.3.dist-info/COPYING.txt
idea_latest-1.0.3.dist-info/LICENSE
idea_latest-1.0.3.dist-info/METADATA
idea_latest-1.0.3.dist-info/WHEEL
idea_latest-1.0.3.dist-info/top_level.txt
idea_latest-1.0.3.dist-info/RECORD
