Metadata-Version: 2.1
Name: iDEA-latest
Version: 1.0.3
Summary: interacting Dynamic Electrons Approach (iDEA)
Home-page: https://idea-org.github.io/
Author: Jack Wetherell
Author-email: jack.wetherell@gmail.com
Project-URL: Bug Tracker, https://github.com/iDEA-org/iDEA/issues
Classifier: Programming Language :: Python :: 3
Classifier: License :: OSI Approved :: GNU General Public License (GPL)
Classifier: Operating System :: OS Independent
Requires-Python: >=3.8
License-File: LICENSE
License-File: COPYING.txt
Requires-Dist: numpy >=1.22.3
Requires-Dist: scipy >=1.8.0
Requires-Dist: matplotlib >=3.5.1
Requires-Dist: jupyterlab >=3.3.2
Requires-Dist: tqdm >=4.64.0
Requires-Dist: black >=22.3.0
Requires-Dist: autoflake >=1.4.0
Requires-Dist: build >=0.7.0
Requires-Dist: twine >=4.0.0
Requires-Dist: pytest >=8.3.0
